pynekoapi/__init__.py
pynekoapi/api/__init__.py
pynekoapi/api/async_nekoapi.py
pynekoapi/api/sync_nekoapi.py
pynekoapi/tools/__init__.py
pynekoapi/tools/async_request.py
pynekoapi/tools/sync_request.py
pynekoapi-0.5.3.dist-info/licenses/LICENSE
pynekoapi-0.5.3.dist-info/METADATA
pynekoapi-0.5.3.dist-info/WHEEL
pynekoapi-0.5.3.dist-info/top_level.txt
pynekoapi-0.5.3.dist-info/RECORD
